attaparse/__init__.py
attaparse/depparse.py
attaparse-0.0.1.dist-info/METADATA
attaparse-0.0.1.dist-info/WHEEL
attaparse-0.0.1.dist-info/top_level.txt
attaparse-0.0.1.dist-info/RECORD
