Metadata-Version: 2.1
Name: attaparse
Version: 0.0.1
Summary: Thai dependency parser.
Author-email: Attapol Thamrongrattanarit <profte@gmail.com>
License: MIT
Project-URL: Homepage, https://github.com/nlp-chula/attaparse
Keywords: python,Thai dependency,Dependency parser
Classifier: Development Status :: 3 - Alpha
Classifier: Intended Audience :: Education
Classifier: Programming Language :: Python :: 3
Classifier: Operating System :: MacOS :: MacOS X
Classifier: Operating System :: Microsoft :: Windows
Requires-Python: >=3.8
Requires-Dist: stanza
